pathfinder_client/__init__.py
pathfinder_client/async_client.py
pathfinder_client/base_client.py
pathfinder_client/constants.py
pathfinder_client/exceptions.py
pathfinder_client/sync_client.py
pathfinder_client/responses/__init__.py
pathfinder_client/responses/base_response.py
pathfinder_client/responses/route_response.py
tests/__init__.py
tests/test_async_client.py
tests/test_geocode.py
tests/test_route.py
tests/test_sync_client.py
pathfinder_client-1.0.7.dist-info/LICENSE.txt
pathfinder_client-1.0.7.dist-info/METADATA
pathfinder_client-1.0.7.dist-info/WHEEL
pathfinder_client-1.0.7.dist-info/top_level.txt
pathfinder_client-1.0.7.dist-info/RECORD
